djangoldp_invoice/__init__.py
djangoldp_invoice/admin.py
djangoldp_invoice/apps.py
djangoldp_invoice/djangoldp_settings.py
djangoldp_invoice/models.py
djangoldp_invoice/views.py
djangoldp_invoice/migrations/0001_initial.py
djangoldp_invoice/migrations/0002_auto_20201015_1121.py
djangoldp_invoice/migrations/0003_auto_20201015_1122.py
djangoldp_invoice/migrations/0004_auto_20201210_0828.py
djangoldp_invoice/migrations/0005_auto_20210112_1008.py
djangoldp_invoice/migrations/0006_auto_20210218_1145.py
djangoldp_invoice/migrations/0007_auto_20210427_1129.py
djangoldp_invoice/migrations/0008_auto_20210427_1155.py
djangoldp_invoice/migrations/0009_auto_20210511_2346.py
djangoldp_invoice/migrations/0010_term.py
djangoldp_invoice/migrations/0011_auto_20210721_1634.py
djangoldp_invoice/migrations/0012_auto_20210730_1420.py
djangoldp_invoice/migrations/__init__.py
djangoldp_invoice/tests/__init__.py
djangoldp_invoice/tests/models.py
djangoldp_invoice/tests/runner.py
djangoldp_invoice/tests/tests_get.py
djangoldp_invoice/tests/tests_permissions.py
djangoldp_invoice/tests/tests_update.py
djangoldp_invoice-2.2.6.dist-info/LICENSE
djangoldp_invoice-2.2.6.dist-info/METADATA
djangoldp_invoice-2.2.6.dist-info/WHEEL
djangoldp_invoice-2.2.6.dist-info/top_level.txt
djangoldp_invoice-2.2.6.dist-info/RECORD
