Metadata-Version: 2.1
Name: djangoldp-invoice
Version: 2.2.6
Summary: djangoldp package for invoicing data models
Home-page: https://git.startinblox.com/djangoldp-packages/djangoldp-invoices
Author: Startin'blox
Author-email: hello@startinblox.com
License: MIT
Platform: UNKNOWN
Requires-Dist: djangoldp (>=2.1.21)
Requires-Dist: djangoldp-project (>=2)
